{
  "statistics": {
    "detectionDate": "2025-06-30T22:14:27.411Z",
    "formats": {
      "javascript": {
        "sources": {
          "/home/runner/workspace/src/utils/motion.js": {
            "lines": 40,
            "tokens": 429,
            "sources": 1,
            "clones": 0,
            "duplicatedLines": 0,
            "duplicatedTokens": 0,
            "percentage": 0,
            "percentageTokens": 0,
            "newDuplicatedLines": 0,
            "newClones": 0
          },
          "/home/runner/workspace/src/types/index.js": {
            "lines": 154,
            "tokens": 1058,
            "sources": 1,
            "clones": 0,
            "duplicatedLines": 0,
            "duplicatedTokens": 0,
            "percentage": 0,
            "percentageTokens": 0,
            "newDuplicatedLines": 0,
            "newClones": 0
          },
          "/home/runner/workspace/src/services/api.js": {
            "lines": 73,
            "tokens": 527,
            "sources": 1,
            "clones": 0,
            "duplicatedLines": 0,
            "duplicatedTokens": 0,
            "percentage": 0,
            "percentageTokens": 0,
            "newDuplicatedLines": 0,
            "newClones": 0
          },
          "/home/runner/workspace/src/context/AppContext.jsx": {
            "lines": 0,
            "tokens": 3,
            "sources": 1,
            "clones": 0,
            "duplicatedLines": 0,
            "duplicatedTokens": 0,
            "percentage": 0,
            "percentageTokens": 0,
            "newDuplicatedLines": 0,
            "newClones": 0
          },
          "/home/runner/workspace/src/config/environment.js": {
            "lines": 37,
            "tokens": 298,
            "sources": 1,
            "clones": 0,
            "duplicatedLines": 0,
            "duplicatedTokens": 0,
            "percentage": 0,
            "percentageTokens": 0,
            "newDuplicatedLines": 0,
            "newClones": 0
          },
          "/home/runner/workspace/src/components/StatusBadge.jsx": {
            "lines": 0,
            "tokens": 9,
            "sources": 1,
            "clones": 0,
            "duplicatedLines": 0,
            "duplicatedTokens": 0,
            "percentage": 0,
            "percentageTokens": 0,
            "newDuplicatedLines": 0,
            "newClones": 0
          },
          "/home/runner/workspace/src/components/Scheduler.jsx": {
            "lines": 88,
            "tokens": 731,
            "sources": 1,
            "clones": 0,
            "duplicatedLines": 0,
            "duplicatedTokens": 0,
            "percentage": 0,
            "percentageTokens": 0,
            "newDuplicatedLines": 0,
            "newClones": 0
          },
          "/home/runner/workspace/src/components/LoadingSpinner.jsx": {
            "lines": 2,
            "tokens": 48,
            "sources": 1,
            "clones": 0,
            "duplicatedLines": 0,
            "duplicatedTokens": 0,
            "percentage": 0,
            "percentageTokens": 0,
            "newDuplicatedLines": 0,
            "newClones": 0
          },
          "/home/runner/workspace/src/components/Layout.jsx": {
            "lines": 65,
            "tokens": 527,
            "sources": 1,
            "clones": 0,
            "duplicatedLines": 0,
            "duplicatedTokens": 0,
            "percentage": 0,
            "percentageTokens": 0,
            "newDuplicatedLines": 0,
            "newClones": 0
          },
          "/home/runner/workspace/src/components/ErrorBoundary.jsx": {
            "lines": 0,
            "tokens": 19,
            "sources": 1,
            "clones": 0,
            "duplicatedLines": 0,
            "duplicatedTokens": 0,
            "percentage": 0,
            "percentageTokens": 0,
            "newDuplicatedLines": 0,
            "newClones": 0
          },
          "/home/runner/workspace/src/components/DataTable.jsx": {
            "lines": 64,
            "tokens": 502,
            "sources": 1,
            "clones": 0,
            "duplicatedLines": 0,
            "duplicatedTokens": 0,
            "percentage": 0,
            "percentageTokens": 0,
            "newDuplicatedLines": 0,
            "newClones": 0
          },
          "/home/runner/workspace/src/components/Dashboard.jsx": {
            "lines": 108,
            "tokens": 862,
            "sources": 1,
            "clones": 0,
            "duplicatedLines": 0,
            "duplicatedTokens": 0,
            "percentage": 0,
            "percentageTokens": 0,
            "newDuplicatedLines": 0,
            "newClones": 0
          },
          "/home/runner/workspace/src/components/Card.jsx": {
            "lines": 3,
            "tokens": 49,
            "sources": 1,
            "clones": 0,
            "duplicatedLines": 0,
            "duplicatedTokens": 0,
            "percentage": 0,
            "percentageTokens": 0,
            "newDuplicatedLines": 0,
            "newClones": 0
          },
          "/home/runner/workspace/src/components/Button.jsx": {
            "lines": 4,
            "tokens": 51,
            "sources": 1,
            "clones": 0,
            "duplicatedLines": 0,
            "duplicatedTokens": 0,
            "percentage": 0,
            "percentageTokens": 0,
            "newDuplicatedLines": 0,
            "newClones": 0
          },
          "/home/runner/workspace/src/App.jsx": {
            "lines": 4,
            "tokens": 98,
            "sources": 1,
            "clones": 0,
            "duplicatedLines": 0,
            "duplicatedTokens": 0,
            "percentage": 0,
            "percentageTokens": 0,
            "newDuplicatedLines": 0,
            "newClones": 0
          }
        },
        "total": {
          "lines": 642,
          "tokens": 5211,
          "sources": 15,
          "clones": 0,
          "duplicatedLines": 0,
          "duplicatedTokens": 0,
          "percentage": 0,
          "percentageTokens": 0,
          "newDuplicatedLines": 0,
          "newClones": 0
        }
      },
      "jsx": {
        "sources": {
          "/home/runner/workspace/src/context/AppContext.jsx": {
            "lines": 166,
            "tokens": 1315,
            "sources": 1,
            "clones": 0,
            "duplicatedLines": 0,
            "duplicatedTokens": 0,
            "percentage": 0,
            "percentageTokens": 0,
            "newDuplicatedLines": 0,
            "newClones": 0
          },
          "/home/runner/workspace/src/components/StatusBadge.jsx": {
            "lines": 24,
            "tokens": 149,
            "sources": 1,
            "clones": 0,
            "duplicatedLines": 0,
            "duplicatedTokens": 0,
            "percentage": 0,
            "percentageTokens": 0,
            "newDuplicatedLines": 0,
            "newClones": 0
          },
          "/home/runner/workspace/src/components/Scheduler.jsx": {
            "lines": 267,
            "tokens": 2037,
            "sources": 1,
            "clones": 0,
            "duplicatedLines": 0,
            "duplicatedTokens": 0,
            "percentage": 0,
            "percentageTokens": 0,
            "newDuplicatedLines": 0,
            "newClones": 0
          },
          "/home/runner/workspace/src/components/LoadingSpinner.jsx": {
            "lines": 39,
            "tokens": 254,
            "sources": 1,
            "clones": 0,
            "duplicatedLines": 0,
            "duplicatedTokens": 0,
            "percentage": 0,
            "percentageTokens": 0,
            "newDuplicatedLines": 0,
            "newClones": 0
          },
          "/home/runner/workspace/src/components/Layout.jsx": {
            "lines": 101,
            "tokens": 871,
            "sources": 1,
            "clones": 0,
            "duplicatedLines": 0,
            "duplicatedTokens": 0,
            "percentage": 0,
            "percentageTokens": 0,
            "newDuplicatedLines": 0,
            "newClones": 0
          },
          "/home/runner/workspace/src/components/ErrorBoundary.jsx": {
            "lines": 51,
            "tokens": 381,
            "sources": 1,
            "clones": 0,
            "duplicatedLines": 0,
            "duplicatedTokens": 0,
            "percentage": 0,
            "percentageTokens": 0,
            "newDuplicatedLines": 0,
            "newClones": 0
          },
          "/home/runner/workspace/src/components/DataTable.jsx": {
            "lines": 103,
            "tokens": 757,
            "sources": 1,
            "clones": 0,
            "duplicatedLines": 0,
            "duplicatedTokens": 0,
            "percentage": 0,
            "percentageTokens": 0,
            "newDuplicatedLines": 0,
            "newClones": 0
          },
          "/home/runner/workspace/src/components/Dashboard.jsx": {
            "lines": 163,
            "tokens": 1321,
            "sources": 1,
            "clones": 4,
            "duplicatedLines": 54,
            "duplicatedTokens": 410,
            "percentage": 33.13,
            "percentageTokens": 31.04,
            "newDuplicatedLines": 0,
            "newClones": 0
          },
          "/home/runner/workspace/src/components/Card.jsx": {
            "lines": 24,
            "tokens": 196,
            "sources": 1,
            "clones": 0,
            "duplicatedLines": 0,
            "duplicatedTokens": 0,
            "percentage": 0,
            "percentageTokens": 0,
            "newDuplicatedLines": 0,
            "newClones": 0
          },
          "/home/runner/workspace/src/components/Button.jsx": {
            "lines": 48,
            "tokens": 294,
            "sources": 1,
            "clones": 0,
            "duplicatedLines": 0,
            "duplicatedTokens": 0,
            "percentage": 0,
            "percentageTokens": 0,
            "newDuplicatedLines": 0,
            "newClones": 0
          },
          "/home/runner/workspace/src/main.jsx": {
            "lines": 10,
            "tokens": 72,
            "sources": 1,
            "clones": 0,
            "duplicatedLines": 0,
            "duplicatedTokens": 0,
            "percentage": 0,
            "percentageTokens": 0,
            "newDuplicatedLines": 0,
            "newClones": 0
          },
          "/home/runner/workspace/src/index.jsx": {
            "lines": 11,
            "tokens": 75,
            "sources": 1,
            "clones": 0,
            "duplicatedLines": 0,
            "duplicatedTokens": 0,
            "percentage": 0,
            "percentageTokens": 0,
            "newDuplicatedLines": 0,
            "newClones": 0
          },
          "/home/runner/workspace/src/App.jsx": {
            "lines": 36,
            "tokens": 309,
            "sources": 1,
            "clones": 0,
            "duplicatedLines": 0,
            "duplicatedTokens": 0,
            "percentage": 0,
            "percentageTokens": 0,
            "newDuplicatedLines": 0,
            "newClones": 0
          }
        },
        "total": {
          "lines": 1043,
          "tokens": 8031,
          "sources": 13,
          "clones": 2,
          "duplicatedLines": 27,
          "duplicatedTokens": 205,
          "percentage": 2.59,
          "percentageTokens": 2.55,
          "newDuplicatedLines": 0,
          "newClones": 0
        }
      }
    },
    "total": {
      "lines": 1685,
      "tokens": 13242,
      "sources": 28,
      "clones": 2,
      "duplicatedLines": 27,
      "duplicatedTokens": 205,
      "percentage": 1.6,
      "percentageTokens": 1.55,
      "newDuplicatedLines": 0,
      "newClones": 0
    }
  },
  "duplicates": [
    {
      "format": "jsx",
      "lines": 15,
      "fragment": ".length}\n                </p>\n              </div>\n            </div>\n          </Card>\n        </motion.div>\n\n        <motion.div\n          initial={{ opacity: 0, y: 20 }}\n          animate={{ opacity: 1, y: 0 }}\n          transition={{ delay: 0.3 }}\n        >\n          <Card>\n            <div className=\"flex items-center p-6\">\n              <div className=\"p-3 bg-orange-100 rounded-lg",
      "tokens": 0,
      "firstFile": {
        "name": "/home/runner/workspace/src/components/Dashboard.jsx",
        "start": 94,
        "end": 108,
        "startLoc": {
          "line": 94,
          "column": 2,
          "position": 804
        },
        "endLoc": {
          "line": 108,
          "column": 29,
          "position": 909
        }
      },
      "secondFile": {
        "name": "/home/runner/workspace/src/components/Dashboard.jsx",
        "start": 72,
        "end": 86,
        "startLoc": {
          "line": 72,
          "column": 6,
          "position": 617
        },
        "endLoc": {
          "line": 86,
          "column": 28,
          "position": 722
        }
      }
    },
    {
      "format": "jsx",
      "lines": 14,
      "fragment": "</p>\n              </div>\n            </div>\n          </Card>\n        </motion.div>\n\n        <motion.div\n          initial={{ opacity: 0, y: 20 }}\n          animate={{ opacity: 1, y: 0 }}\n          transition={{ delay: 0.4 }}\n        >\n          <Card>\n            <div className=\"flex items-center p-6\">\n              <div className=\"p-3 bg-purple-100 rounded-lg",
      "tokens": 0,
      "firstFile": {
        "name": "/home/runner/workspace/src/components/Dashboard.jsx",
        "start": 115,
        "end": 128,
        "startLoc": {
          "line": 115,
          "column": 2,
          "position": 973
        },
        "endLoc": {
          "line": 128,
          "column": 29,
          "position": 1073
        }
      },
      "secondFile": {
        "name": "/home/runner/workspace/src/components/Dashboard.jsx",
        "start": 73,
        "end": 86,
        "startLoc": {
          "line": 73,
          "column": 17,
          "position": 622
        },
        "endLoc": {
          "line": 86,
          "column": 28,
          "position": 722
        }
      }
    }
  ]
}